cajal/sample_mesh.py
cajal/wnn.py
cajal/weighted_tree.py
cajal/run_gw.py
cajal/__init__.py
cajal/combined_slb_qgw.py
cajal/swc.py
cajal/ternary.py
cajal/EMD_wrapper.cpp
cajal/sample_seg.py
cajal/slb.cpython-312-darwin.so
cajal/sample_swc.py
cajal/gw_cython.cpython-312-darwin.so
cajal/EMD.h
cajal/partial.py
cajal/utilities.py
cajal/laplacian_score.py
cajal/fused_gw_swc.py
cajal/slb.cpp
cajal/gw_cython.cpp
cajal/cajal_types.py
cajal/qgw.py
cajal/deformation_vis.py
cajal/ugw/__init__.py
cajal/ugw/_multicore.abi3.so
cajal/ugw/build_backends.py
cajal/ugw/_single_core.abi3.so
cajal-1.5.dist-info/LICENSE.md
cajal-1.5.dist-info/RECORD
cajal-1.5.dist-info/WHEEL
cajal-1.5.dist-info/top_level.txt
cajal-1.5.dist-info/METADATA
