Metadata-Version: 2.2
Name: cajal
Version: 1.5
Summary: A library for multi-modal cell morphology analyses using Gromov-Wasserstein (GW) distance.
Author-email: Pablo Cámara <pcamara@pennmedicine.upenn.edu>
License: MIT License
Project-URL: git-repo, https://github.com/CamaraLab/CAJAL
Project-URL: readthedocs, https://cajal.readthedocs.io/en/latest/
Project-URL: biorxiv, https://www.biorxiv.org/content/10.1101/2022.05.19.492525v2
Classifier: License :: OSI Approved :: MIT License
Classifier: Programming Language :: Python :: 3
Classifier: Framework :: Jupyter
Classifier: Topic :: Scientific/Engineering :: Bio-Informatics
Requires-Python: >=3.9
License-File: LICENSE.md
Requires-Dist: igraph
Requires-Dist: leidenalg
Requires-Dist: numpy
Requires-Dist: cython>=3
Requires-Dist: pathos>=0.3.2
Requires-Dist: futhark-ffi>=0.15
Requires-Dist: tqdm>=4.64.1
Requires-Dist: potpourri3d
Requires-Dist: pynndescent>=0.5.13
Requires-Dist: navis>=1.9.0
Requires-Dist: python-louvain
Requires-Dist: pot
Requires-Dist: pillow>=11.0
Requires-Dist: scipy>=1.10
Requires-Dist: scikit-image
Requires-Dist: tifffile
Requires-Dist: trimesh
Requires-Dist: mpltern>=1.0.0
Requires-Dist: scikit-dimension
Provides-Extra: dev
Requires-Dist: mypy>=0.991; extra == "dev"
Requires-Dist: pytest>=7.2.1; extra == "dev"
Requires-Dist: pre-commit>=2.20.0; extra == "dev"
Requires-Dist: myst_parser; extra == "dev"
Requires-Dist: plotly; extra == "dev"
Requires-Dist: nbsphinx; extra == "dev"
Requires-Dist: navis; extra == "dev"
Requires-Dist: black; extra == "dev"
Requires-Dist: flake8; extra == "dev"
Requires-Dist: ipywidgets; extra == "dev"
Requires-Dist: sphinx_rtd_theme; extra == "dev"
Provides-Extra: doc
Requires-Dist: sphinx; extra == "doc"
Requires-Dist: myst_parser; extra == "doc"
Requires-Dist: nbsphinx; extra == "doc"
Requires-Dist: sphinx_rtd_theme; extra == "doc"
Requires-Dist: pandas; extra == "doc"
Requires-Dist: plotly; extra == "doc"
Provides-Extra: vis
Requires-Dist: networkx>=3; extra == "vis"
Requires-Dist: ipywidgets; extra == "vis"
Requires-Dist: navis; extra == "vis"
Requires-Dist: mpltern; extra == "vis"
Requires-Dist: plotly; extra == "vis"
Provides-Extra: notebooks
Requires-Dist: networkx>=3; extra == "notebooks"
Requires-Dist: ipywidgets; extra == "notebooks"
Requires-Dist: navis; extra == "notebooks"
Requires-Dist: numba; extra == "notebooks"
Requires-Dist: mpltern; extra == "notebooks"
Requires-Dist: plotly; extra == "notebooks"
Requires-Dist: umap-learn; extra == "notebooks"
Requires-Dist: scanpy; extra == "notebooks"
